msqlite/__init__.py
msqlite/msqlite.py
msqlite/py.typed
msqlite-0.5.0.dist-info/LICENSE
msqlite-0.5.0.dist-info/METADATA
msqlite-0.5.0.dist-info/WHEEL
msqlite-0.5.0.dist-info/top_level.txt
msqlite-0.5.0.dist-info/RECORD
