Metadata-Version: 2.2
Name: msqlite
Version: 0.5.0
Summary: Execute simple SQLite statements that are multithreaded/multiprocess safe
Author-email: James Abel <j@abel.co>
License: MIT License
Project-URL: Source, https://github.com/jamesabel/msqlite
Keywords: sqlite,multithread,multiprocess
Classifier: Programming Language :: Python :: 3
Classifier: License :: OSI Approved :: MIT License
Classifier: Operating System :: OS Independent
Requires-Python: >=3.10
License-File: LICENSE
